bitcoin_karishma/__init__.py
bitcoin_karishma/run.py
bitcoin_karishma-1.1.1.dist-info/LICENSE
bitcoin_karishma-1.1.1.dist-info/METADATA
bitcoin_karishma-1.1.1.dist-info/WHEEL
bitcoin_karishma-1.1.1.dist-info/entry_points.txt
bitcoin_karishma-1.1.1.dist-info/top_level.txt
bitcoin_karishma-1.1.1.dist-info/RECORD
