Metadata-Version: 2.1
Name: bitcoin-karishma
Version: 1.1.1
Summary: A Python package to get bitcoin updates and predictions
Home-page: https://github.com/karishma-garg-au7/bitcoin_notification
Author: Karishma Agarwal
Author-email: karishmaag21@gmail.com
License: MIT
Platform: UNKNOWN
Classifier: License :: OSI Approved :: MIT License
Classifier: Programming Language :: Python :: 3
Classifier: Programming Language :: Python :: 3.7
Requires-Dist: requests
Requires-Dist: datetime
